sorl/__init__.py
sorl/thumbnail/__init__.py
sorl/thumbnail/base.py
sorl/thumbnail/default.py
sorl/thumbnail/fields.py
sorl/thumbnail/helpers.py
sorl/thumbnail/images.py
sorl/thumbnail/log.py
sorl/thumbnail/models.py
sorl/thumbnail/parsers.py
sorl/thumbnail/shortcuts.py
sorl/thumbnail/admin/__init__.py
sorl/thumbnail/admin/current.py
sorl/thumbnail/conf/__init__.py
sorl/thumbnail/conf/defaults.py
sorl/thumbnail/engines/__init__.py
sorl/thumbnail/engines/base.py
sorl/thumbnail/engines/convert_engine.py
sorl/thumbnail/engines/pgmagick_engine.py
sorl/thumbnail/engines/pil_engine.py
sorl/thumbnail/engines/vipsthumbnail_engine.py
sorl/thumbnail/engines/wand_engine.py
sorl/thumbnail/kvstores/__init__.py
sorl/thumbnail/kvstores/base.py
sorl/thumbnail/kvstores/cached_db_kvstore.py
sorl/thumbnail/kvstores/dbm_kvstore.py
sorl/thumbnail/kvstores/dynamodb_kvstore.py
sorl/thumbnail/kvstores/redis_kvstore.py
sorl/thumbnail/management/__init__.py
sorl/thumbnail/management/commands/__init__.py
sorl/thumbnail/management/commands/thumbnail.py
sorl/thumbnail/migrations/0001_initial.py
sorl/thumbnail/migrations/__init__.py
sorl/thumbnail/templatetags/__init__.py
sorl/thumbnail/templatetags/sorl_thumbnail.py
sorl/thumbnail/templatetags/thumbnail.py
sorl_thumbnail-12.11.0.dist-info/AUTHORS.rst
sorl_thumbnail-12.11.0.dist-info/LICENSE
sorl_thumbnail-12.11.0.dist-info/METADATA
sorl_thumbnail-12.11.0.dist-info/WHEEL
sorl_thumbnail-12.11.0.dist-info/top_level.txt
sorl_thumbnail-12.11.0.dist-info/RECORD
