Metadata-Version: 2.1
Name: sorl-thumbnail
Version: 12.11.0
Summary: Thumbnails for Django
Author-email: Mikko Hellsing <mikko@aino.se>
Maintainer-email: Jazzband <roadies@jazzband.co>
License: Copyright (c) 2010, Mikko Hellsing
Project-URL: Homepage, https://sorl-thumbnail.readthedocs.io/en/latest/
Project-URL: Repository, https://github.com/jazzband/sorl-thumbnail
Keywords: django,thumbnail,sorl
Classifier: Development Status :: 5 - Production/Stable
Classifier: Environment :: Web Environment
Classifier: Intended Audience :: Developers
Classifier: License :: OSI Approved :: BSD License
Classifier: Operating System :: OS Independent
Classifier: Programming Language :: Python
Classifier: Programming Language :: Python :: 3.8
Classifier: Programming Language :: Python :: 3.9
Classifier: Programming Language :: Python :: 3.10
Classifier: Programming Language :: Python :: 3.11
Classifier: Programming Language :: Python :: 3.12
Classifier: Topic :: Internet :: WWW/HTTP :: Dynamic Content
Classifier: Topic :: Multimedia :: Graphics
Classifier: Framework :: Django
Classifier: Framework :: Django :: 4.2
Classifier: Framework :: Django :: 5.0
Classifier: Framework :: Django :: 5.1
Requires-Python: >=3.8
License-File: LICENSE
License-File: AUTHORS.rst
Provides-Extra: pgmagick
Requires-Dist: pgmagick; extra == "pgmagick"
Provides-Extra: pil
Requires-Dist: pillow; extra == "pil"
Provides-Extra: wand
Requires-Dist: wand; extra == "wand"
